integration_tests/__init__.py
integration_tests/abnormal_state.json
integration_tests/acceptance.py
integration_tests/configured_catalog.json
integration_tests/integration_test.py
integration_tests/invalid_config.json
source_zuora/__init__.py
source_zuora/run.py
source_zuora/source.py
source_zuora/spec.json
source_zuora/zuora_auth.py
source_zuora/zuora_endpoint.py
source_zuora/zuora_errors.py
source_zuora/zuora_excluded_streams.py
airbyte_source_zuora-0.1.3.dist-info/METADATA
airbyte_source_zuora-0.1.3.dist-info/WHEEL
airbyte_source_zuora-0.1.3.dist-info/entry_points.txt
airbyte_source_zuora-0.1.3.dist-info/top_level.txt
airbyte_source_zuora-0.1.3.dist-info/RECORD
