Metadata-Version: 2.1
Name: airbyte-source-zuora
Version: 0.1.3
Summary: Airbyte source-connector for Zuora.
Author: Airbyte
Author-email: contact@airbyte.io
Requires-Dist: airbyte-cdk
Requires-Dist: pendulum
Provides-Extra: tests
Requires-Dist: requests-mock ~=1.9.3 ; extra == 'tests'
Requires-Dist: pytest-mock ~=3.6.1 ; extra == 'tests'
